{
  "dataset_revision": "main",
  "task_name": "MSMarcoTRRetrieval",
  "mteb_version": "1.31.3",
  "scores": {
    "test": [
      {
        "ndcg_at_1": 0.56039,
        "ndcg_at_3": 0.57784,
        "ndcg_at_5": 0.57948,
        "ndcg_at_10": 0.58118,
        "ndcg_at_20": 0.58129,
        "ndcg_at_100": 0.58162,
        "ndcg_at_1000": 0.58169,
        "map_at_1": 0.56039,
        "map_at_3": 0.574,
        "map_at_5": 0.57493,
        "map_at_10": 0.57561,
        "map_at_20": 0.57564,
        "map_at_100": 0.57567,
        "map_at_1000": 0.57567,
        "recall_at_1": 0.56039,
        "recall_at_3": 0.58875,
        "recall_at_5": 0.59267,
        "recall_at_10": 0.59804,
        "recall_at_20": 0.59853,
        "recall_at_100": 0.60049,
        "recall_at_1000": 0.60098,
        "precision_at_1": 0.56039,
        "precision_at_3": 0.19625,
        "precision_at_5": 0.11853,
        "precision_at_10": 0.0598,
        "precision_at_20": 0.02993,
        "precision_at_100": 0.006,
        "precision_at_1000": 0.0006,
        "mrr_at_1": 0.560391,
        "mrr_at_3": 0.574002,
        "mrr_at_5": 0.574931,
        "mrr_at_10": 0.575608,
        "mrr_at_20": 0.575636,
        "mrr_at_100": 0.575666,
        "mrr_at_1000": 0.57567,
        "nauc_ndcg_at_1_max": 0.87531,
        "nauc_ndcg_at_1_std": 0.185295,
        "nauc_ndcg_at_1_diff1": 0.895334,
        "nauc_ndcg_at_3_max": 0.877758,
        "nauc_ndcg_at_3_std": 0.193609,
        "nauc_ndcg_at_3_diff1": 0.876014,
        "nauc_ndcg_at_5_max": 0.877361,
        "nauc_ndcg_at_5_std": 0.197922,
        "nauc_ndcg_at_5_diff1": 0.87386,
        "nauc_ndcg_at_10_max": 0.875591,
        "nauc_ndcg_at_10_std": 0.200995,
        "nauc_ndcg_at_10_diff1": 0.872171,
        "nauc_ndcg_at_20_max": 0.875505,
        "nauc_ndcg_at_20_std": 0.201434,
        "nauc_ndcg_at_20_diff1": 0.872085,
        "nauc_ndcg_at_100_max": 0.875113,
        "nauc_ndcg_at_100_std": 0.201667,
        "nauc_ndcg_at_100_diff1": 0.871735,
        "nauc_ndcg_at_1000_max": 0.874998,
        "nauc_ndcg_at_1000_std": 0.201665,
        "nauc_ndcg_at_1000_diff1": 0.871649,
        "nauc_map_at_1_max": 0.87531,
        "nauc_map_at_1_std": 0.185295,
        "nauc_map_at_1_diff1": 0.895334,
        "nauc_map_at_3_max": 0.877277,
        "nauc_map_at_3_std": 0.191475,
        "nauc_map_at_3_diff1": 0.880277,
        "nauc_map_at_5_max": 0.877055,
        "nauc_map_at_5_std": 0.193907,
        "nauc_map_at_5_diff1": 0.879073,
        "nauc_map_at_10_max": 0.876359,
        "nauc_map_at_10_std": 0.19506,
        "nauc_map_at_10_diff1": 0.878417,
        "nauc_map_at_20_max": 0.876338,
        "nauc_map_at_20_std": 0.195163,
        "nauc_map_at_20_diff1": 0.878397,
        "nauc_map_at_100_max": 0.876303,
        "nauc_map_at_100_std": 0.195185,
        "nauc_map_at_100_diff1": 0.878365,
        "nauc_map_at_1000_max": 0.876296,
        "nauc_map_at_1000_std": 0.195185,
        "nauc_map_at_1000_diff1": 0.87836,
        "nauc_recall_at_1_max": 0.87531,
        "nauc_recall_at_1_std": 0.185295,
        "nauc_recall_at_1_diff1": 0.895334,
        "nauc_recall_at_3_max": 0.87912,
        "nauc_recall_at_3_std": 0.199911,
        "nauc_recall_at_3_diff1": 0.863704,
        "nauc_recall_at_5_max": 0.878157,
        "nauc_recall_at_5_std": 0.210341,
        "nauc_recall_at_5_diff1": 0.858424,
        "nauc_recall_at_10_max": 0.872427,
        "nauc_recall_at_10_std": 0.220656,
        "nauc_recall_at_10_diff1": 0.852834,
        "nauc_recall_at_20_max": 0.872052,
        "nauc_recall_at_20_std": 0.222566,
        "nauc_recall_at_20_diff1": 0.852448,
        "nauc_recall_at_100_max": 0.869595,
        "nauc_recall_at_100_std": 0.224052,
        "nauc_recall_at_100_diff1": 0.850222,
        "nauc_recall_at_1000_max": 0.868789,
        "nauc_recall_at_1000_std": 0.224054,
        "nauc_recall_at_1000_diff1": 0.849602,
        "nauc_precision_at_1_max": 0.87531,
        "nauc_precision_at_1_std": 0.185295,
        "nauc_precision_at_1_diff1": 0.895334,
        "nauc_precision_at_3_max": 0.87912,
        "nauc_precision_at_3_std": 0.199911,
        "nauc_precision_at_3_diff1": 0.863704,
        "nauc_precision_at_5_max": 0.878157,
        "nauc_precision_at_5_std": 0.210341,
        "nauc_precision_at_5_diff1": 0.858424,
        "nauc_precision_at_10_max": 0.872427,
        "nauc_precision_at_10_std": 0.220656,
        "nauc_precision_at_10_diff1": 0.852834,
        "nauc_precision_at_20_max": 0.872052,
        "nauc_precision_at_20_std": 0.222566,
        "nauc_precision_at_20_diff1": 0.852448,
        "nauc_precision_at_100_max": 0.869595,
        "nauc_precision_at_100_std": 0.224052,
        "nauc_precision_at_100_diff1": 0.850222,
        "nauc_precision_at_1000_max": 0.868789,
        "nauc_precision_at_1000_std": 0.224054,
        "nauc_precision_at_1000_diff1": 0.849602,
        "nauc_mrr_at_1_max": 0.87531,
        "nauc_mrr_at_1_std": 0.185295,
        "nauc_mrr_at_1_diff1": 0.895334,
        "nauc_mrr_at_3_max": 0.877277,
        "nauc_mrr_at_3_std": 0.191475,
        "nauc_mrr_at_3_diff1": 0.880277,
        "nauc_mrr_at_5_max": 0.877055,
        "nauc_mrr_at_5_std": 0.193907,
        "nauc_mrr_at_5_diff1": 0.879073,
        "nauc_mrr_at_10_max": 0.876359,
        "nauc_mrr_at_10_std": 0.19506,
        "nauc_mrr_at_10_diff1": 0.878417,
        "nauc_mrr_at_20_max": 0.876338,
        "nauc_mrr_at_20_std": 0.195163,
        "nauc_mrr_at_20_diff1": 0.878397,
        "nauc_mrr_at_100_max": 0.876303,
        "nauc_mrr_at_100_std": 0.195185,
        "nauc_mrr_at_100_diff1": 0.878365,
        "nauc_mrr_at_1000_max": 0.876296,
        "nauc_mrr_at_1000_std": 0.195185,
        "nauc_mrr_at_1000_diff1": 0.87836,
        "main_score": 0.58118,
        "hf_subset": "default",
        "languages": [
          "tur-Latn"
        ]
      }
    ]
  },
  "evaluation_time": 12.08242917060852,
  "kg_co2_emissions": null
}